libdyson/__init__.py
libdyson/const.py
libdyson/discovery.py
libdyson/dyson_360_eye.py
libdyson/dyson_360_heurist.py
libdyson/dyson_device.py
libdyson/dyson_pure_cool.py
libdyson/dyson_pure_cool_link.py
libdyson/dyson_pure_hot_cool.py
libdyson/dyson_pure_hot_cool_link.py
libdyson/dyson_pure_humidify_cool.py
libdyson/dyson_vacuum_device.py
libdyson/exceptions.py
libdyson/utils.py
libdyson/cloud/__init__.py
libdyson/cloud/account.py
libdyson/cloud/cloud_360_eye.py
libdyson/cloud/cloud_device.py
libdyson/cloud/device_info.py
libdyson/cloud/regions.py
libdyson/cloud/utils.py
tests/__init__.py
tests/conftest.py
tests/mocked_mqtt.py
tests/test_360_eye.py
tests/test_360_heurist.py
tests/test_device.py
tests/test_discovery.py
tests/test_fan_device.py
tests/test_heating_device.py
tests/test_init.py
tests/test_pure_cool.py
tests/test_pure_cool_formaldehyde.py
tests/test_pure_cool_link.py
tests/test_pure_hot_cool_link.py
tests/test_pure_humidify_cool.py
tests/test_purifier_humidify_cool_formaldehyde.py
tests/test_utils.py
tests/test_vacuum.py
tests/cloud/__init__.py
tests/cloud/conftest.py
tests/cloud/mocked_requests.py
tests/cloud/test_bearer_auth.py
tests/cloud/test_cloud_360_eye.py
tests/cloud/test_dyson_account.py
tests/cloud/utils.py
logan_libdyson-0.8.13.dist-info/LICENSE
logan_libdyson-0.8.13.dist-info/METADATA
logan_libdyson-0.8.13.dist-info/WHEEL
logan_libdyson-0.8.13.dist-info/top_level.txt
logan_libdyson-0.8.13.dist-info/RECORD
