Metadata-Version: 2.1
Name: logan-libdyson
Version: 0.8.13
Summary: A Python library for Dyson devices.
Home-page: https://github.com/iml885203/libdyson
Author: Logan
Author-email: iml885203@gmail.com
License: MIT License
Keywords: dyson
Platform: any
Classifier: Intended Audience :: Developers
Classifier: License :: OSI Approved :: MIT License
Classifier: Operating System :: OS Independent
Classifier: Programming Language :: Python :: 3.8
License-File: LICENSE
Requires-Dist: paho-mqtt
Requires-Dist: cryptography (>=3.1)
Requires-Dist: requests
Requires-Dist: zeroconf
Requires-Dist: attrs
